LICENSE
MANIFEST.in
README.md
pyproject.toml
requirements.txt
setup.py
daskpeeker/__init__.py
daskpeeker/_version.py
daskpeeker/default_report.py
daskpeeker/elem_ids.py
daskpeeker/peeker_class.py
daskpeeker/peeker_layout.py
daskpeeker/report_classes.py
daskpeeker/style.py
daskpeeker/util.py
daskpeeker/view_store.py
daskpeeker.egg-info/PKG-INFO
daskpeeker.egg-info/SOURCES.txt
daskpeeker.egg-info/dependency_links.txt
daskpeeker.egg-info/requires.txt
daskpeeker.egg-info/top_level.txt
daskpeeker/tests/__init__.py
daskpeeker/tests/data_for_testing.py
daskpeeker/tests/peeker_for_testing.py
daskpeeker/tests/test_basics.py
daskpeeker/tests/test_import.py