Metadata-Version: 2.1
Name: daskpeeker
Version: 0.0.0
Summary: Dashboard to view slices of dask dataframes
Home-page: https://github.com/endremborza/daskpeeker
Author: Endre Márk Borza
License: MIT
Keywords: dask
Platform: any
Classifier: License :: OSI Approved :: MIT License
Requires-Python: >=3.7
